thingwala/geyserwala/__init__.py
thingwala/geyserwala/const.py
thingwala/geyserwala/errors.py
thingwala/geyserwala/aio/__init__.py
thingwala/geyserwala/aio/cli.py
thingwala/geyserwala/aio/client.py
thingwala/geyserwala/aio/discovery.py
thingwala_geyserwala-0.0.9.dist-info/licenses/LICENSE
thingwala_geyserwala-0.0.9.dist-info/METADATA
thingwala_geyserwala-0.0.9.dist-info/WHEEL
thingwala_geyserwala-0.0.9.dist-info/entry_points.txt
thingwala_geyserwala-0.0.9.dist-info/top_level.txt
thingwala_geyserwala-0.0.9.dist-info/RECORD
