Metadata-Version: 2.4
Name: thingwala-geyserwala
Version: 0.0.9
Summary: Python bindings to the Geyserwala REST API
Home-page: https://github.com/thingwala/geyserwala-py
Author: Thingwala
License: MIT
License-File: LICENSE
Requires-Dist: aiohttp
Requires-Dist: zeroconf
Dynamic: author
Dynamic: home-page
Dynamic: license
Dynamic: license-file
Dynamic: requires-dist
Dynamic: summary
